kinisot/Hess_to_Freq.py
kinisot/Kinisot.py
kinisot/__init__.py
kinisot/__main__.py
kinisot/vib_scale_factors.py
kinisot/examples/CH3F_F_rc.out
kinisot/examples/CH3F_F_ts.out
kinisot/examples/Cl_H_Cl_RCT.out
kinisot/examples/Cl_H_Cl_TS.out
kinisot/examples/claisen_gs.out
kinisot/examples/claisen_ts.out
kinisot-2.0.1.dist-info/LICENSE.txt
kinisot-2.0.1.dist-info/METADATA
kinisot-2.0.1.dist-info/WHEEL
kinisot-2.0.1.dist-info/top_level.txt
kinisot-2.0.1.dist-info/RECORD
